{"authorDailyContributionsMap":{"mohamedirfansh":[{"date":"2021-09-30","commitResults":[{"hash":"a24f05dbe69ef223993e36141db3d42860511b2e","messageTitle":"Add contributor name","messageBody":"","fileTypesAndContributionMap":{"docs":{"insertions":1,"deletions":0}}}]}],"ZhangErliCarl":[{"date":"2021-09-30","commitResults":[{"hash":"2bae302d7740788fa7a78718340b9fd9a41326a8","messageTitle":"commit","messageBody":"","fileTypesAndContributionMap":{"docs":{"insertions":1,"deletions":0}}}]}],"husysg":[{"date":"2021-09-30","commitResults":[{"hash":"116e640b69b86a6f7991fcd2b928f719d5a8e621","messageTitle":"new edit","messageBody":"","fileTypesAndContributionMap":{"docs":{"insertions":1,"deletions":0}}}]}],"Journeyman1998":[{"date":"2021-09-30","commitResults":[{"hash":"9c8d974e9eda2820ff3725c7deaa7e4f10d4e4de","messageTitle":"New edit","messageBody":"","fileTypesAndContributionMap":{"docs":{"insertions":1,"deletions":1}}}]}]},"authorFileTypeContributionMap":{"mohamedirfansh":{"docs":1,"functional-code":0,"test-code":0},"ZhangErliCarl":{"docs":1,"functional-code":0,"test-code":0},"husysg":{"docs":1,"functional-code":0,"test-code":0},"Journeyman1998":{"docs":1,"functional-code":0,"test-code":0}},"authorContributionVariance":{"mohamedirfansh":0.13888888,"ZhangErliCarl":0.13888888,"husysg":0.13888888,"Journeyman1998":0.5555555},"authorDisplayNameMap":{"mohamedirfansh":"CS2113-T16-4 MOHA..MEED","ZhangErliCarl":"CS2113-T16-4 ZHAN..ERLI","husysg":"CS2113-T16-4 HU S..YUAN","Journeyman1998":"CS2113-T16-4 TNG .. WEI"}}
